src/__init__.py
src/constants.py
src/exceptions.py
src/main.py
src/templates/base_structure.json
src/templates/root_structure.json
src/utils/__init__.py
src/utils/custom_parser.py
src/utils/structure_creation.py
src/utils/structure_generation.py
src/utils/structure_loader.py
src/utils/structure_migration.py
src/utils/structure_utils.py
src/utils/validation.py
microservice_setup-0.2.1.dist-info/LICENSE
microservice_setup-0.2.1.dist-info/METADATA
microservice_setup-0.2.1.dist-info/WHEEL
microservice_setup-0.2.1.dist-info/entry_points.txt
microservice_setup-0.2.1.dist-info/RECORD
