Metadata-Version: 2.1
Name: microservice-setup
Version: 0.2.1
Summary: Automatically generate a hexagonal architecture project structure for microservices in Python.
License: LICENSE
Author: DoMo
Author-email: ericdominguezm@gmail.com
Requires-Python: >=3.9,<4.0
Classifier: License :: Other/Proprietary License
Classifier: Programming Language :: Python :: 3
Classifier: Programming Language :: Python :: 3.9
Classifier: Programming Language :: Python :: 3.10
Classifier: Programming Language :: Python :: 3.11
